jsonspice/__init__.py
jsonspice/main.py
jsonspice-1.2.0.dist-info/METADATA
jsonspice-1.2.0.dist-info/WHEEL
jsonspice-1.2.0.dist-info/licenses/LICENSE
jsonspice-1.2.0.dist-info/RECORD
