Metadata-Version: 2.4
Name: jsonspice
Version: 1.2.0
Summary: Python library to monkeypatch SpiceyPy to allow JSON kernels.
Project-URL: Homepage, https://github.com/jacobwilliams/jsonspice
Project-URL: Issues, https://github.com/jacobwilliams/jsonspice/issues
Project-URL: documentation, https://jacobwilliams.github.io/jsonspice
License: MIT License
License-File: LICENSE
Requires-Python: >=3.8
Requires-Dist: json5
Requires-Dist: spiceypy
